LICENSE
MANIFEST.in
pyproject.toml
setup.py
cmfrec/__init__.py
cmfrec/cfuns_double.pyx
cmfrec/cfuns_double_plusblas.pyx
cmfrec/cfuns_float.pyx
cmfrec/cfuns_float_plusblas.pyx
cmfrec/cython_cblas.pxi
cmfrec/wrapper_untyped.pxi
cmfrec.egg-info/PKG-INFO
cmfrec.egg-info/SOURCES.txt
cmfrec.egg-info/dependency_links.txt
cmfrec.egg-info/requires.txt
cmfrec.egg-info/top_level.txt
src/arithmetic_ansi.h
src/cblas_wrappers.c
src/cmfrec.h
src/collective.c
src/common.c
src/helpers.c
src/lbfgs.c
src/lbfgs.h
src/offsets.c
src/ziggurat.h