Metadata-Version: 2.1
Name: cmfrec
Version: 3.5.1.post13
Summary: Collective matrix factorization
Home-page: https://github.com/david-cortes/cmfrec
Author: David Cortes
Keywords: collaborative filtering,collective matrix factorization,relational learning
License-File: LICENSE
Requires-Dist: cython
Requires-Dist: numpy>=1.25
Requires-Dist: scipy
Requires-Dist: pandas
Requires-Dist: findblas
